csockets-4.2.29.dist-info/LICENSE
csockets-4.2.29.dist-info/METADATA
csockets-4.2.29.dist-info/RECORD
csockets-4.2.29.dist-info/WHEEL
csockets-4.2.29.dist-info/top_level.txt
csockets/__init__.pyi
csockets/socket.pyi
csockets\__init__.pyc
csockets\_connection.pyc
csockets\_encryption.pyc
csockets\_protocols.pyc
csockets\socket.pyc
