Metadata-Version: 2.1
Name: csockets
Version: 4.2.29
Summary: Fast non-blocking socket implementation in C.
Author-email: Mana Danele <manadanele@gmail.com>
Keywords: sockets,networking
Classifier: Programming Language :: Python :: 3
Classifier: Operating System :: OS Independent
Requires-Python: >=3.9
License-File: LICENSE
